CleanInput/__init__.py
CleanInput/clean_input.py
InputClean-0.1.0.dist-info/METADATA
InputClean-0.1.0.dist-info/WHEEL
InputClean-0.1.0.dist-info/top_level.txt
InputClean-0.1.0.dist-info/RECORD
