Metadata-Version: 2.1
Name: InputClean
Version: 0.1.0
Summary: Auto del input noise.
Author: KurehaSHO
Classifier: Programming Language :: Python :: 3
Classifier: Operating System :: OS Independent
Requires-Python: >=3.0
